setup.py
downTool/__init__.py
downTool/downtool.py
downtool.egg-info/PKG-INFO
downtool.egg-info/SOURCES.txt
downtool.egg-info/dependency_links.txt
downtool.egg-info/requires.txt
downtool.egg-info/top_level.txt